{
  "data": [
    {
      "__v": 0,
      "_id": "product-1",
      "name": "Product 1 Cat 1",
      "image": "assets/img/prod-1.jpg",
      "description": "Product 1 belongs to Category 1",
      "category_id": "category-1",
      "price": 200,
      "discount": 0.1,
      "rating": 4.5,
      "rating_count": 32,
      "is_featured": true,
      "is_recent": false
    },
    {
      "__v": 0,
      "_id": "product-2",
      "name": "Product 2 Cat 1",
      "image": "assets/img/prod-2.jpg",
      "description": "Product 2 belongs to Category 1",
      "category_id": "category-1",
      "price": 300,
      "discount": 0.2,
      "rating": 3.5,
      "rating_count": 71,
      "is_featured": false,
      "is_recent": false
    },
    {
      "__v": 0,
      "_id": "product-3",
      "name": "Product 3 Cat 1",
      "image": "assets/img/prod-3.jpg",
      "description": "Product 3 belongs to Category 1",
      "category_id": "category-1",
      "price": 120,
      "discount": 0.8,
      "rating": 4,
      "rating_count": 23,
      "is_featured": false,
      "is_recent": true
    },
    {
      "__v": 0,
      "_id": "product-4",
      "name": "Product 4 Cat 2",
      "image": "assets/img/prod-4.jpg",
      "description": "Product 4 belongs to Category 2",
      "category_id": "category-2",
      "price": 599,
      "discount": 0.4,
      "rating": 5,
      "rating_count": 59,
      "is_featured": true,
      "is_recent": true
    },
    {
      "__v": 0,
      "_id": "product-5",
      "name": "Product 5 Cat 2",
      "image": "assets/img/prod-5.jpg",
      "description": "Product 5 belongs to Category 2",
      "category_id": "category-2",
      "price": 300,
      "discount": 0.2,
      "rating": 2.5,
      "rating_count": 10,
      "is_featured": false,
      "is_recent": true
    },
    {
      "__v": 0,
      "_id": "product-6",
      "name": "Product 6 Cat 2",
      "image": "assets/img/prod-6.jpg",
      "category_id": "category-2",
      "description": "Product 6 belongs to Category 2",
      "price": 500,
      "discount": 0.01,
      "rating": 4.5,
      "rating_count": 90,
      "is_featured": true,
      "is_recent": false
    },
    {
      "__v": 0,
      "_id": "product-7",
      "name": "Product 7 Cat 2",
      "image": "assets/img/prod-7.jpg",
      "category_id": "category-2",
      "description": "Product 7 belongs to Category 2",
      "price": 100,
      "discount": 0.1,
      "rating": 4.5,
      "rating_count": 150,
      "is_featured": false,
      "is_recent": false
    },
    {
      "__v": 0,
      "_id": "product-8",
      "name": "Product 8 Cat 3",
      "image": "assets/img/prod-8.jpg",
      "category_id": "category-3",
      "description": "Product 8 belongs to Category 3",
      "price": 1300,
      "discount": 0.25,
      "rating": 3.5,
      "rating_count": 421,
      "is_featured": false,
      "is_recent": false
    },
    {
      "__v": 0,
      "_id": "product-9",
      "name": "Product 9 Cat 4",
      "image": "assets/img/prod-9.jpg",
      "category_id": "category-4",
      "description": "Product 9 belongs to Category 4",
      "price": 1000,
      "discount": 0.5,
      "rating": 1,
      "rating_count": 311,
      "is_featured": false,
      "is_recent": false
    }
  ]
}
